oslo_service/__init__.py
oslo_service/_i18n.py
oslo_service/_options.py
oslo_service/eventlet_backdoor.py
oslo_service/fixture.py
oslo_service/loopingcall.py
oslo_service/periodic_task.py
oslo_service/service.py
oslo_service/sslutils.py
oslo_service/systemd.py
oslo_service/threadgroup.py
oslo_service/version.py
oslo_service/wsgi.py
oslo_service/backend/__init__.py
oslo_service/backend/base.py
oslo_service/backend/exceptions.py
oslo_service/backend/_common/__init__.py
oslo_service/backend/_common/constants.py
oslo_service/backend/_common/loopingcall.py
oslo_service/backend/_common/service.py
oslo_service/backend/_common/threadgroup.py
oslo_service/backend/_eventlet/__init__.py
oslo_service/backend/_eventlet/loopingcall.py
oslo_service/backend/_eventlet/service.py
oslo_service/backend/_eventlet/threadgroup.py
oslo_service/backend/_threading/__init__.py
oslo_service/backend/_threading/loopingcall.py
oslo_service/backend/_threading/service.py
oslo_service/backend/_threading/threadgroup.py
oslo_service/locale/en_GB/LC_MESSAGES/oslo_service.po
oslo_service/tests/__init__.py
oslo_service/tests/base.py
oslo_service/tests/eventlet_service.py
oslo_service/tests/test_eventlet_backdoor.py
oslo_service/tests/test_fixture.py
oslo_service/tests/test_loopingcall.py
oslo_service/tests/test_periodic.py
oslo_service/tests/test_service.py
oslo_service/tests/test_sslutils.py
oslo_service/tests/test_systemd.py
oslo_service/tests/test_threadgroup.py
oslo_service/tests/test_wsgi.py
oslo_service/tests/backend/__init__.py
oslo_service/tests/backend/tests/__init__.py
oslo_service/tests/backend/tests/test_backend_base.py
oslo_service/tests/backend/tests/test_backend_init.py
oslo_service/tests/backend/threading/__init__.py
oslo_service/tests/backend/threading/test_launcher.py
oslo_service/tests/ssl_cert/ca.crt
oslo_service/tests/ssl_cert/ca.key
oslo_service/tests/ssl_cert/certificate.crt
oslo_service/tests/ssl_cert/privatekey.key
oslo_service-4.4.0.dist-info/AUTHORS
oslo_service-4.4.0.dist-info/LICENSE
oslo_service-4.4.0.dist-info/METADATA
oslo_service-4.4.0.dist-info/WHEEL
oslo_service-4.4.0.dist-info/entry_points.txt
oslo_service-4.4.0.dist-info/pbr.json
oslo_service-4.4.0.dist-info/top_level.txt
oslo_service-4.4.0.dist-info/RECORD
