Metadata-Version: 2.1
Name: oslo.service
Version: 4.4.0
Summary: oslo.service library
Author-email: OpenStack <openstack-discuss@lists.openstack.org>
Project-URL: Homepage, https://docs.openstack.org/oslo.service
Project-URL: Repository, https://opendev.org/openstack/oslo.service
Classifier: Environment :: OpenStack
Classifier: Intended Audience :: Information Technology
Classifier: Intended Audience :: System Administrators
Classifier: License :: OSI Approved :: Apache Software License
Classifier: Operating System :: POSIX :: Linux
Classifier: Programming Language :: Python
Classifier: Programming Language :: Python :: 3
Classifier: Programming Language :: Python :: 3.10
Classifier: Programming Language :: Python :: 3.11
Classifier: Programming Language :: Python :: 3.12
Classifier: Programming Language :: Python :: 3.13
Classifier: Programming Language :: Python :: 3 :: Only
Classifier: Programming Language :: Python :: Implementation :: CPython
Requires-Python: >=3.10
License-File: LICENSE
License-File: AUTHORS
Requires-Dist: WebOb >=1.7.1
Requires-Dist: debtcollector >=1.2.0
Requires-Dist: eventlet >=0.27.0
Requires-Dist: greenlet >=0.4.15
Requires-Dist: oslo.utils >=3.40.2
Requires-Dist: oslo.concurrency >=3.25.0
Requires-Dist: oslo.config >=5.1.0
Requires-Dist: oslo.log >=3.36.0
Requires-Dist: oslo.i18n >=3.15.3
Requires-Dist: PasteDeploy >=1.5.0
Requires-Dist: Routes >=2.3.1
Requires-Dist: Paste >=2.0.2
Requires-Dist: Yappi >=1.0
Provides-Extra: threading
Requires-Dist: cotyledon >=2.0.0 ; extra == 'threading'
Requires-Dist: futurist >=3.1.1 ; extra == 'threading'
